vimeo_downloader/__init__.py
vimeo_downloader-0.4.1.dist-info/WHEEL
vimeo_downloader-0.4.1.dist-info/METADATA
vimeo_downloader-0.4.1.dist-info/RECORD
