Metadata-Version: 2.1
Name: vimeo-downloader
Version: 0.4.1
Summary: Download videos and retrieve metadata from Vimeo.
Home-page: https://github.com/yashrathi-git/vimeo_downloader
License: MIT
Keywords: vimeo,vimeo-api,vimeo meta data,vimeo downloader,vimeo_downloader
Author: Yash Rathi
Author-email: yashrathicricket@gmail.com
Requires-Python: >=3.6.2,<4
Classifier: License :: OSI Approved :: MIT License
Classifier: Programming Language :: Python :: 3
Classifier: Programming Language :: Python :: 3.10
Classifier: Programming Language :: Python :: 3.7
Classifier: Programming Language :: Python :: 3.8
Classifier: Programming Language :: Python :: 3.9
Requires-Dist: requests (>=2.26.0,<3.0.0)
Requires-Dist: tqdm (>=4.62.3,<5.0.0)
Requires-Dist: urllib3 (>=1.26); python_version >= "3.10" and python_version < "4"
Project-URL: Bug Tracker, https://github.com/yashrathi-git/vimeo_downloader/issues
Project-URL: Documentation, https://github.com/yashrathi-git/vimeo_downloader#readme
